dakara_player/__init__.py
dakara_player/__main__.py
dakara_player/audio.py
dakara_player/background.py
dakara_player/font.py
dakara_player/manager.py
dakara_player/mrl.py
dakara_player/player.py
dakara_player/text.py
dakara_player/user_resources.py
dakara_player/version.py
dakara_player/web_client.py
dakara_player/window.py
dakara_player/media_player/__init__.py
dakara_player/media_player/base.py
dakara_player/media_player/mpv.py
dakara_player/media_player/vlc.py
dakara_player/resources/__init__.py
dakara_player/resources/line-awesome.json
dakara_player/resources/player.yaml
dakara_player/resources/backgrounds/__init__.py
dakara_player/resources/backgrounds/idle.png
dakara_player/resources/backgrounds/transition.png
dakara_player/resources/fonts/Roboto-Light.ttf
dakara_player/resources/fonts/Roboto-Thin.ttf
dakara_player/resources/fonts/__init__.py
dakara_player/resources/fonts/la-solid-900.ttf
dakara_player/resources/templates/__init__.py
dakara_player/resources/templates/idle.ass
dakara_player/resources/templates/transition.ass
dakaraplayer-1.9.0.dist-info/LICENSE
dakaraplayer-1.9.0.dist-info/METADATA
dakaraplayer-1.9.0.dist-info/WHEEL
dakaraplayer-1.9.0.dist-info/entry_points.txt
dakaraplayer-1.9.0.dist-info/top_level.txt
dakaraplayer-1.9.0.dist-info/RECORD
