Metadata-Version: 2.2
Name: dakaraplayer
Version: 1.9.0
Summary: Media player for the Dakara Project
Author-email: Flore <flore.love@gmail.com>, Neraste <neraste.herr10@gmail.com>
License: The MIT License (MIT)
Project-URL: Homepage, https://github.com/DakaraProject/dakara-player
Project-URL: Repository, https://github.com/DakaraProject/dakara-player.git
Project-URL: Issues, https://github.com/DakaraProject/dakara-player/issues
Project-URL: Changelog, https://github.com/DakaraProject/dakara-player/blob/master/CHANGELOG.md
Classifier: License :: OSI Approved :: MIT License
Classifier: Programming Language :: Python
Classifier: Programming Language :: Python :: 3
Classifier: Programming Language :: Python :: 3.9
Classifier: Programming Language :: Python :: 3.10
Classifier: Programming Language :: Python :: 3.11
Classifier: Programming Language :: Python :: 3.12
Classifier: Programming Language :: Python :: 3.13
Classifier: Operating System :: OS Independent
Classifier: Environment :: X11 Applications
Classifier: Environment :: Win32 (MS Windows)
Classifier: Intended Audience :: End Users/Desktop
Requires-Python: >=3.9
License-File: LICENSE
Requires-Dist: Jinja2<3.2.0,>=3.1.1
Requires-Dist: dakarabase<2.2.0,>=2.1.0
Requires-Dist: filetype<1.3.0,>=1.2.0
Requires-Dist: packaging<25.0,>=24.2
Requires-Dist: python-mpv-jsonipc<1.3.0,>=1.2.0
Requires-Dist: python-vlc!=3.0.12117,<3.1.0,>=3.0.21203
Provides-Extra: dev
Requires-Dist: black<25.2.0,>=25.1.0; extra == "dev"
Requires-Dist: codecov<2.2.0,>=2.1.13; extra == "dev"
Requires-Dist: func_timeout<4.4.0,>=4.3.5; extra == "dev"
Requires-Dist: isort<6.1.0,>=6.0.0; extra == "dev"
Requires-Dist: pdoc<15.1.0,>=15.0.1; extra == "dev"
Requires-Dist: pre-commit<4.2.0,>=4.1.0; extra == "dev"
Requires-Dist: pytest-cov<6.1.0,>=6.0.0; extra == "dev"
Requires-Dist: pytest<8.4.0,>=8.3.4; extra == "dev"
Requires-Dist: ruff<0.10.0,>=0.9.6; extra == "dev"
